pulpcore/__init__.py
pulpcore/client/__init__.py
pulpcore/client/pulp_file/__init__.py
pulpcore/client/pulp_file/api_client.py
pulpcore/client/pulp_file/api_response.py
pulpcore/client/pulp_file/configuration.py
pulpcore/client/pulp_file/exceptions.py
pulpcore/client/pulp_file/py.typed
pulpcore/client/pulp_file/rest.py
pulpcore/client/pulp_file/api/__init__.py
pulpcore/client/pulp_file/api/acs_file_api.py
pulpcore/client/pulp_file/api/content_files_api.py
pulpcore/client/pulp_file/api/distributions_file_api.py
pulpcore/client/pulp_file/api/publications_file_api.py
pulpcore/client/pulp_file/api/remotes_file_api.py
pulpcore/client/pulp_file/api/repositories_file_api.py
pulpcore/client/pulp_file/api/repositories_file_versions_api.py
pulpcore/client/pulp_file/models/__init__.py
pulpcore/client/pulp_file/models/async_operation_response.py
pulpcore/client/pulp_file/models/content_summary_response.py
pulpcore/client/pulp_file/models/file_content_upload_response.py
pulpcore/client/pulp_file/models/file_file_alternate_content_source.py
pulpcore/client/pulp_file/models/file_file_alternate_content_source_response.py
pulpcore/client/pulp_file/models/file_file_content_response.py
pulpcore/client/pulp_file/models/file_file_distribution.py
pulpcore/client/pulp_file/models/file_file_distribution_response.py
pulpcore/client/pulp_file/models/file_file_publication.py
pulpcore/client/pulp_file/models/file_file_publication_response.py
pulpcore/client/pulp_file/models/file_file_remote.py
pulpcore/client/pulp_file/models/file_file_remote_response.py
pulpcore/client/pulp_file/models/file_file_remote_response_hidden_fields_inner.py
pulpcore/client/pulp_file/models/file_file_repository.py
pulpcore/client/pulp_file/models/file_file_repository_response.py
pulpcore/client/pulp_file/models/my_permissions_response.py
pulpcore/client/pulp_file/models/nested_role.py
pulpcore/client/pulp_file/models/nested_role_response.py
pulpcore/client/pulp_file/models/object_roles_response.py
pulp_file_client-3.100.0.dist-info/METADATA
pulp_file_client-3.100.0.dist-info/WHEEL
pulp_file_client-3.100.0.dist-info/top_level.txt
pulp_file_client-3.100.0.dist-info/RECORD
